Metadata-Version: 1.1
Name: handyinfer
Version: 0.0.4
Summary: Handy inference
Home-page: https://github.com/xinntao/HandyInfer
Author: Xintao Wang
Author-email: xintao.wang@outlook.com
License: Apache License 2.0
Keywords: computer vision
Platform: UNKNOWN
Classifier: Development Status :: 4 - Beta
Classifier: License :: OSI Approved :: Apache Software License
Classifier: Operating System :: OS Independent
Classifier: Programming Language :: Python :: 3
Classifier: Programming Language :: Python :: 3.7
Classifier: Programming Language :: Python :: 3.8
